Workbook

Sheet Original_Data
A1: store_id | B1: month | C1: region | D1: store_type | E1: marketing_spend | F1: footfall | G1: avg_discount_pct | H1: staff_count | I1: inventory_availability_pct | J1: competitor_distance_km | K1: holiday_flag | L1: customer_rating | M1: monthly_sales | N1: monthly_profit
A2: STR-1001 | B2: 45658 | C2: East | D2: Residential | E2: 70389.11 | F2: 8302 | G2: 0.042 | H2: 17 | I2: 75 | J2: 5.28 | K2: 1 | L2: 3.1 | M2: 658832.62 | N2: 84349.93
A3: STR-1001 | B3: 45689 | C3: East | D3: Residential | E3: 43827.89 | F3: 8487 | G3: 0.168 | H3: 23 | I3: 84.4 | J3: 4.31 | K3: 0 | L3: 2.8 | M3: 634436 | N3: 106130.54
A4: STR-1001 | B4: 45717 | C4: East | D4: Residential | E4: 59921.75 | F4: 9113 | G4: 0.133 | H4: 20 | I4: 88 | J4: 12 | K4: 0 | L4: 3.2 | M4: 678722.06 | N4: 101883.86
A5: STR-1001 | B5: 45748 | C5: East | D5: Residential | E5: 56856.63 | F5: 9431 | G5: 0.142 | H5: 23 | I5: 86.9 | J5: 4.97 | K5: 0 | L5: 3.4 | M5: 658920.3 | N5: 97910.37
A6: STR-1002 | B6: 45658 | C6: East | D6: High Street | E6: 48412.64 | F6: 9545 | G6: 0.231 | H6: 21 | I6: 97.6 | J6: 6.94 | K6: 1 | L6: 4.2 | M6: 741341.44 | N6: 119208.17
A7: STR-1002 | B7: 45689 | C7: East | D7: High Street | E7: 64811.21 | F7: 9792 | G7: 0.112 | H7: 20 | I7: 84.2 | J7: 2.88 | K7: 0 | L7: 4.2 | M7: 761835.34 | N7: 149602.23
A8: STR-1002 | B8: 45717 | C8: East | D8: High Street | E8: 46213.45 | F8: 10616 | G8: 0.122 | H8: 22 | I8: 85.2 | J8: 0.2 | K8: 1 | L8: 4.1 | M8: 806615.54 | N8: 131364.62
A9: STR-1002 | B9: 45748 | C9: East | D9: High Street | E9: 68148.52 | F9: 8567 | G9: 0.127 | H9: 23 | I9: 95.6 | J9: 0.8 | K9: 0 | L9: 3.9 | M9: 850164.26 | N9: 149262.75
A10: STR-1003 | B10: 45658 | C10: North | D10: Airport | E10: 71838.86 | F10: 10979 | G10: 0.215 | H10: 26 | I10: 88.6 | J10: 7.7 | K10: 1 | L10: 3.8 | M10: 930581.7 | N10: 136207.98
A11: STR-1003 | B11: 45689 | C11: North | D11: Airport | E11: 68133.44 | F11: 9459 | G11: 0.22 | H11: 21 | I11: 85 | J11: 1.91 | K11: 0 | L11: 4.2 | M11: 779010.94 | N11: 106328.09
A12: STR-1003 | B12: 45717 | C12: North | D12: Airport | E12: 34285.21 | F12: 9172 | G12: 0.213 | H12: 22 | I12: 88.3 | J12: 10.46 | K12: 1 | L12: 3.8 | M12: 723060.76 | N12: 123131.24
A13: STR-1003 | B13: 45748 | C13: North | D13: Airport | E13: 67979.88 | F13: 11230 | G13: 0.002 | H13: 28 | I13: 85.3 | J13: 7.16 | K13: 0 | L13: 3.8 | M13: 910791.94 | N13: 158891.28
... A34: STR-1009 | B34: 45658 | C34: North | D34: Residential | E34: 54597.83 | F34: 9429 | G34: 0.188 | H34: 21 | I34: 83.3 | J34: 11.71 | K34: 0 | L34: 4.2 | M34: 641865.03 | N34: 81342.58
A35: STR-1009 | B35: 45689 | C35: North | D35: Residential | E35: 73771.91 | F35: 11695 | G35: 0.07 | H35: 25 | I35: 84.7 | J35: 0.62 | K35: 0 | M35: 799477.76 | N35: 164974.41
A36: STR-1009 | B36: 45717 | C36: North | D36: Residential | E36: 74413.88 | F36: 9449 | G36: 0.039 | H36: 23 | I36: 92.1 | J36: 2.12 | K36: 0 | L36: 3.5 | M36: 798952.17 | N36: 161499.04
A37: STR-1009 | B37: 45748 | C37: North | D37: Residential | E37: 52483.77 | F37: 10453 | G37: 0.247 | H37: 25 | I37: 99 | J37: 6.31 | K37: 0 | L37: 3.6 | M37: 800979.78 | N37: 149242.27
A38: STR-1010 | B38: 45658 | C38: North | D38: Mall | E38: 75269.87 | F38: 8838 | G38: 0.092 | H38: 21 | I38: 83.1 | J38: 9.56 | K38: 1 | L38: 4.2 | M38: 820593.93 | N38: 115860.06
A39: STR-1010 | B39: 45689 | C39: North | D39: Mall | E39: 61245.41 | F39: 8156 | G39: 0.156 | H39: 19 | I39: 92.9 | J39: 9.05 | K39: 0 | L39: 3.8 | M39: 718330.53 | N39: 93247.9
A40: STR-1010 | B40: 45717 | C40: North | D40: Mall | E40: 93381.26 | F40: 7562 | G40: 0.198 | H40: 19 | I40: 82.9 | J40: 5.05 | K40: 0 | L40: 4 | M40: 736633.4 | N40: 115654.66
A41: STR-1010 | B41: 45748 | C41: North | D41: Mall | E41: 65012.19 | F41: 9598 | G41: 0.085 | H41: 24 | I41: 98.3 | J41: 0.89 | K41: 0 | L41: 3.8 | M41: 828623.85 | N41: 167320.52
A42: STR-1011 | B42: 45658 | C42: East | D42: Mall | E42: 40462.94 | F42: 3660 | G42: 0.218 | H42: 11 | I42: 95.2 | J42: 5.57 | K42: 0 | L42: 4.4 | M42: 592195.85 | N42: 92291.56
A43: STR-1011 | B43: 45689 | C43: East | D43: Mall | E43: 46123.88 | F43: 3227 | G43: 0.143 | H43: 10 | I43: 75.4 | J43: 1.06 | K43: 0 | L43: 4.4 | M43: 532644.46 | N43: 60681.32
A44: STR-1011 | B44: 45717 | C44: East | D44: Mall | E44: 68077.54 | F44: 3360 | G44: 0.128 | H44: 14 | I44: 88.2 | J44: 1.24 | K44: 1 | L44: 4 | M44: 657429.18 | N44: 88919.74
A45: STR-1011 | B45: 45748 | C45: East | D45: Mall | E45: 64882.14 | F45: 3642 | G45: 0.019 | H45: 13 | I45: 87.8 | J45: 4.52 | K45: 0 | L45: 4.2 | M45: 605178 | N45: 106958.74
A46: STR-1012 | B46: 45658 | C46: West | D46: Residential | E46: 138855.51 | F46: 5145 | G46: 0.06 | H46: 17 | I46: 88.2 | J46: 9.58 | K46: 0 | L46: 3.2 | M46: 595467.6 | N46: 104276.46
A47: STR-1012 | B47: 45689 | C47: West | D47: Residential | E47: 63630.21 | F47: 4460 | G47: 0.235 | H47: 14 | I47: 98.6 | J47: 5.52 | K47: 0 | L47: 3.5 | M47: 599603.4 | N47: 112685.12
... A72: STR-1018 | B72: 45717 | C72: East | D72: High Street | E72: 60571.82 | F72: 3193 | G72: 0.197 | H72: 7 | I72: 99 | J72: 1.43 | K72: 0 | L72: 3.2 | M72: 605023.87 | N72: 98545.81
A73: STR-1018 | B73: 45748 | C73: East | D73: High Street | E73: 55081.16 | F73: 5485 | G73: 0.036 | H73: 12 | I73: 88 | K73: 0 | L73: 3.5 | M73: 674774.09 | N73: 141917.59
A74: STR-1019 | B74: 45658 | C74: East | D74: Residential | E74: 46201.46 | F74: 5918 | G74: 0.277 | H74: 13 | I74: 78.8 | J74: 4.91 | K74: 0 | L74: 4.5 | M74: 616069.41 | N74: 54453.99
A75: STR-1019 | B75: 45689 | C75: East | D75: Residential | E75: 53762.92 | F75: 6821 | G75: 0.066 | H75: 19 | I75: 94.6 | J75: 7.03 | K75: 0 | L75: 4.4 | M75: 630829.94 | N75: 117090.02
A76: STR-1019 | B76: 45717 | C76: East | D76: Residential | E76: 70144.78 | F76: 6806 | G76: 0.178 | H76: 20 | I76: 93.1 | J76: 0.28 | K76: 1 | L76: 4.3 | M76: 788087.68 | N76: 116803.42
A77: STR-1019 | B77: 45748 | C77: East | D77: Residential | E77: 58749.63 | F77: 8252 | G77: 0.203 | H77: 20 | I77: 85.2 | J77: 3.61 | K77: 0 | L77: 4.5 | M77: 680840.36 | N77: 68007.68
A78: STR-1020 | B78: 45658 | C78: South | D78: High Street | E78: 56973.18 | F78: 6662 | G78: 0.1 | H78: 15 | I78: 77.7 | J78: 7.52 | K78: 1 | L78: 3.2 | M78: 643657.47 | N78: 87022.45
A79: STR-1020 | B79: 45689 | C79: South | D79: High Street | E79: 54872.82 | F79: 5962 | G79: 0.064 | H79: 12 | I79: 85.4 | J79: 2.58 | K79: 0 | L79: 2.9 | M79: 691112.6 | N79: 109212.83
A80: STR-1020 | B80: 45717 | C80: South | D80: High Street | E80: 80562.81 | F80: 7470 | G80: 0.172 | H80: 16 | I80: 83.5 | J80: 2.29 | K80: 0 | L80: 3.3 | M80: 776922.17 | N80: 150701.93
A81: STR-1020 | B81: 45748 | C81: South | D81: High Street | E81: 77999.9 | F81: 5974 | G81: 0.252 | H81: 14 | I81: 81.3 | J81: 2.39 | K81: 0 | L81: 3.2 | M81: 636561.34 | N81: 93861.06
A82: STR-1021 | B82: 45658 | C82: West | D82: Mall | E82: 60881.01 | F82: 5410 | G82: 0.179 | H82: 15 | I82: 83.9 | J82: 5.24 | K82: 0 | L82: 4.6 | M82: 621369.58 | N82: 85493.64
A83: STR-1021 | B83: 45689 | C83: West | D83: Mall | E83: 60628.38 | F83: 4451 | G83: 0.095 | H83: 10 | I83: 89.6 | J83: 3.17 | K83: 0 | L83: 4.6 | M83: 682208.01 | N83: 110318.84
A84: STR-1021 | B84: 45717 | C84: West | D84: Mall | E84: 72731.14 | F84: 4644 | G84: 0.084 | H84: 15 | I84: 87.1 | J84: 2.66 | K84: 0 | L84: 4.6 | M84: 727241.86 | N84: 155810.3
A85: STR-1021 | B85: 45748 | C85: West | D85: Mall | E85: 36475.71 | F85: 3559 | G85: 0.03 | H85: 8 | I85: 83.6 | J85: 1.41 | K85: 0 | L85: 4.2 | M85: 569100.78 | N85: 104808.78
A86: STR-1022 | B86: 45658 | C86: West | D86: High Street | E86: 55388.11 | F86: 3091 | G86: 0.108 | H86: 7 | I86: 85.4 | J86: 7.34 | K86: 0 | L86: 4.9 | M86: 574436.29 | N86: 80271.99
A87: STR-1022 | B87: 45689 | C87: West | D87: High Street | E87: 88443.77 | F87: 4004 | G87: 0.206 | H87: 11 | I87: 91.9 | J87: 5.95 | K87: 0 | M87: 611766.72 | N87: 88275.61
A88: STR-1022 | B88: 45717 | C88: West | D88: High Street | E88: 78231.91 | F88: 3788 | G88: 0.059 | H88: 11 | I88: 88.5 | J88: 15.51 | K88: 0 | L88: 4.3 | M88: 614596.32 | N88: 131199.41
A89: STR-1022 | B89: 45748 | C89: West | D89: High Street | E89: 18996.32 | F89: 1260 | G89: 0.145 | H89: 9 | I89: 86.4 | J89: 4.31 | K89: 0 | L89: 4.6 | M89: 450711.92 | N89: 90043.76
A90: STR-1023 | B90: 45658 | C90: South | D90: Mall | E90: 50517.94 | F90: 7024 | G90: 0.029 | H90: 18 | I90: 79.2 | J90: 6.61 | K90: 1 | L90: 4.1 | M90: 711213.46 | N90: 105863.26
A91: STR-1023 | B91: 45689 | C91: South | D91: Mall | E91: 141540.29 | F91: 5400 | G91: 0.013 | H91: 12 | I91: 87 | J91: 4.26 | K91: 0 | L91: 4.5 | M91: 627171.9 | N91: 105772.75
A92: STR-1023 | B92: 45717 | C92: South | D92: Mall | E92: 82116.19 | F92: 5988 | G92: 0.04 | H92: 17 | I92: 91.8 | J92: 5.75 | K92: 0 | L92: 4.7 | M92: 739852.58 | N92: 129386.43
A93: STR-1023 | B93: 45748 | C93: South | D93: Mall | E93: 31207.51 | F93: 3701 | G93: 0.043 | H93: 11 | I93: 84.7 | J93: 0.33 | K93: 0 | L93: 4.3 | M93: 586307.22 | N93: 73927.85
A94: STR-1024 | B94: 45658 | C94: West | D94: Residential | E94: 38966.59 | F94: 4509 | G94: 0.194 | H94: 14 | I94: 91.1 | J94: 2.92 | K94: 0 | L94: 4.6 | M94: 585937.48 | N94: 82624.2
A95: STR-1024 | B95: 45689 | C95: West | D95: Residential | E95: 67439.3 | F95: 6477 | G95: 0 | H95: 16 | I95: 90.9 | J95: 1.64 | K95: 0 | L95: 4.5 | M95: 753473.55 | N95: 151527.22
A96: STR-1024 | B96: 45717 | C96: West | D96: Residential | E96: 86421.88 | F96: 7970 | G96: 0.073 | H96: 17 | I96: 91.3 | J96: 0.8 | K96: 0 | L96: 5 | M96: 838250.32 | N96: 122939.34
A97: STR-1024 | B97: 45748 | C97: West | D97: Residential | E97: 9534.65 | F97: 6057 | G97: 0.074 | H97: 15 | I97: 94.1 | J97: 5.79 | K97: 0 | L97: 4.5 | M97: 607898.12 | N97: 135404.85
A98: STR-1025 | B98: 45658 | C98: West | D98: Mall | E98: 61132.07 | F98: 6394 | G98: 0.163 | H98: 19 | I98: 91 | J98: 19.6 | K98: 0 | L98: 4.4 | M98: 691113.62 | N98: 135145.44
A99: STR-1025 | B99: 45689 | C99: West | D99: Mall | E99: 78839.39 | F99: 5150 | G99: 0.171 | H99: 13 | I99: 85.8 | J99: 7.57 | K99: 0 | L99: 4.3 | M99: 735509.4 | N99: 83895.96
A100: STR-1025 | B100: 45717 | C100: West | D100: Mall | E100: 38752.8 | F100: 4712 | G100: 0.075 | H100: 15 | I100: 89.7 | K100: 0 | L100: 4.3 | M100: 605775.33 | N100: 107194.6
A101: STR-1025 | B101: 45748 | C101: West | D101: Mall | E101: 55101.1 | F101: 5281 | G101: 0.189 | H101: 11 | I101: 91 | J101: 2.7 | K101: 0 | L101: 4.4 | M101: 675177.68 | N101: 105628.68
A102: STR-1026 | B102: 45658 | C102: East | D102: Mall | E102: 53084.76 | F102: 3642 | G102: 0.15 | H102: 12 | I102: 91.4 | J102: 0.2 | K102: 0 | L102: 4.4 | M102: 635181.35 | N102: 83341.25
A103: STR-1026 | B103: 45689 | C103: East | D103: Mall | E103: 63101.59 | F103: 4373 | G103: 0.173 | H103: 14 | I103: 90.4 | J103: 7.87 | K103: 0 | L103: 4.7 | M103: 586626.94 | N103: 86498.55
A104: STR-1026 | B104: 45717 | C104: East | D104: Mall | E104: 90084.4 | F104: 6832 | G104: 0.185 | H104: 14 | I104: 80.5 | J104: 0.77 | K104: 1 | L104: 4.4 | M104: 740102.64 | N104: 114299.07
A105: STR-1026 | B105: 45748 | C105: East | D105: Mall | E105: 32266.64 | F105: 2414 | G105: 0.08 | H105: 7 | I105: 92.1 | J105: 1.48 | K105: 0 | L105: 5 | M105: 625514.04 | N105: 120685.08
A106: STR-1027 | B106: 45658 | C106: West | D106: High Street | E106: 57919.07 | F106: 7374 | G106: 0.103 | H106: 21 | I106: 82.3 | J106: 2.87 | K106: 0 | L106: 2.9 | M106: 727227.2 | N106: 121292.01
A107: STR-1027 | B107: 45689 | C107: West | D107: High Street | E107: 74679.35 | F107: 8739 | G107: 0.056 | H107: 21 | I107: 91.8 | J107: 2.83 | K107: 0 | L107: 3 | M107: 783797.89 | N107: 157620.7
A108: STR-1027 | B108: 45717 | C108: West | D108: High Street | E108: 64294.23 | F108: 6992 | G108: 0.133 | H108: 14 | I108: 94.1 | J108: 0.25 | K108: 0 | L108: 3 | M108: 795153.84 | N108: 143194.21
A109: STR-1027 | B109: 45748 | C109: West | D109: High Street | E109: 31042.03 | F109: 7107 | G109: 0.051 | H109: 15 | I109: 87 | J109: 13.33 | K109: 0 | L109: 3.2 | M109: 665594.94 | N109: 127597.34
A110: STR-1028 | B110: 45658 | C110: East | D110: Mall | E110: 75265.02 | F110: 6975 | G110: 0.157 | H110: 20 | I110: 73.8 | J110: 6.35 | K110: 1 | L110: 3.8 | M110: 709478.39 | N110: 71294.27
A111: STR-1028 | B111: 45689 | C111: East | D111: Mall | E111: 69411.7 | F111: 5493 | G111: 0.292 | H111: 13 | I111: 86.5 | J111: 6.69 | K111: 0 | L111: 3.8 | M111: 664162.49 | N111: 98291.06
A112: STR-1028 | B112: 45717 | C112: East | D112: Mall | E112: 51056.15 | F112: 5686 | G112: 0.089 | H112: 13 | I112: 89.9 | J112: 1.28 | K112: 0 | L112: 4.2 | M112: 633494.21 | N112: 105739.47
... A134: STR-1034 | B134: 45658 | C134: North | D134: High Street | E134: 70276.28 | F134: 3043 | G134: 0.079 | H134: 9 | I134: 87.9 | J134: 3.77 | K134: 0 | L134: 4.4 | M134: 527300.13 | N134: 84197.87
A135: STR-1034 | B135: 45689 | C135: North | D135: High Street | E135: 22071.64 | F135: 1814 | G135: 0.196 | H135: 8 | I135: 81.1 | J135: 0.78 | K135: 0 | M135: 400831.65 | N135: 70979.31
A136: STR-1034 | B136: 45717 | C136: North | D136: High Street | E136: 52285.45 | F136: 3618 | G136: 0.086 | H136: 11 | I136: 95.6 | J136: 5.17 | K136: 1 | L136: 4.4 | M136: 593247.25 | N136: 81240.29
A137: STR-1034 | B137: 45748 | C137: North | D137: High Street | E137: 70366.76 | F137: 1963 | G137: 0.182 | H137: 8 | I137: 89.8 | J137: 3.2 | K137: 0 | L137: 4.6 | M137: 529075.95 | N137: 95978.83
A138: STR-1035 | B138: 45658 | C138: South | D138: Residential | E138: 71320.66 | F138: 7888 | G138: 0.048 | H138: 20 | I138: 78.1 | J138: 3.4 | K138: 0 | M138: 633638.03 | N138: 99402.01
A139: STR-1035 | B139: 45689 | C139: South | D139: Residential | E139: 75109.67 | F139: 6244 | G139: 0.079 | H139: 15 | I139: 96.3 | J139: 7.38 | K139: 0 | L139: 3.7 | M139: 743348.84 | N139: 104186.09
A140: STR-1035 | B140: 45717 | C140: South | D140: Residential | E140: 69779 | F140: 6544 | G140: 0.152 | H140: 18 | I140: 90.2 | J140: 0.85 | K140: 1 | L140: 3.3 | M140: 758827.64 | N140: 161439.48
A141: STR-1035 | B141: 45748 | C141: South | D141: Residential | E141: 44211.95 | F141: 5465 | G141: 0.187 | H141: 12 | I141: 90 | J141: 2.89 | K141: 0 | L141: 3.6 | M141: 646559.71 | N141: 97981.75
A142: STR-1036 | B142: 45658 | C142: West | D142: High Street | E142: 51430.31 | F142: 6427 | G142: 0.234 | H142: 14 | I142: 88.8 | J142: 0.77 | K142: 0 | L142: 4.1 | M142: 715890.53 | N142: 109032.15
A143: STR-1036 | B143: 45689 | C143: West | D143: High Street | E143: 45706.49 | F143: 6704 | G143: 0.038 | H143: 15 | I143: 94.2 | J143: 2.92 | K143: 0 | L143: 4.2 | M143: 715097.57 | N143: 151875.86
A144: STR-1036 | B144: 45717 | C144: West | D144: High Street | E144: 44034.6 | F144: 5645 | G144: 0.069 | H144: 18 | I144: 88.5 | J144: 3.07 | K144: 0 | L144: 3.8 | M144: 682639.28 | N144: 77557.53
A145: STR-1036 | B145: 45748 | C145: West | D145: High Street | E145: 50198.12 | F145: 6089 | G145: 0.182 | H145: 19 | I145: 94 | J145: 9.7 | K145: 0 | L145: 3.9 | M145: 695098.51 | N145: 108192.75
A146: STR-1037 | B146: 45658 | C146: North | D146: Residential | E146: 70488.2 | F146: 4312 | G146: 0.169 | H146: 12 | I146: 90.2 | J146: 3.71 | K146: 0 | L146: 3.2 | M146: 577732.57 | N146: 93804.27
A147: STR-1037 | B147: 45689 | C147: North | D147: Residential | E147: 50909.27 | F147: 3152 | G147: 0.06 | H147: 13 | I147: 93.7 | J147: 10.79 | K147: 0 | L147: 3.5 | M147: 537058.33 | N147: 93555.71
A148: STR-1037 | B148: 45717 | C148: North | D148: Residential | E148: 53351.7 | F148: 4259 | G148: 0.156 | H148: 15 | I148: 93.7 | J148: 6.03 | K148: 0 | L148: 3.4 | M148: 601568.87 | N148: 91634.82
A149: STR-1037 | B149: 45748 | C149: North | D149: Residential | E149: 60322.4 | F149: 3350 | G149: 0.108 | H149: 12 | I149: 89.4 | J149: 4.92 | K149: 0 | L149: 3.4 | M149: 570964.84 | N149: 81331.07
A150: STR-1038 | B150: 45658 | C150: South | D150: Mall | E150: 51575.68 | F150: 5329 | G150: 0.047 | H150: 17 | I150: 88.1 | J150: 19.78 | K150: 0 | L150: 3.8 | M150: 614024.91 | N150: 84828.93
... A163: STR-1041 | B163: 45689 | C163: South | D163: High Street | E163: 48438.85 | F163: 6992 | G163: 0.034 | H163: 20 | I163: 91 | J163: 4.36 | K163: 0 | L163: 4.2 | M163: 778298.88 | N163: 130076.72
A164: STR-1041 | B164: 45717 | C164: South | D164: High Street | E164: 57143.3 | F164: 8038 | G164: 0.193 | H164: 17 | I164: 72.6 | K164: 0 | L164: 4.2 | M164: 677096.71 | N164: 97174.11
A165: STR-1041 | B165: 45748 | C165: South | D165: High Street | E165: 66870.62 | F165: 6055 | G165: 0.075 | H165: 19 | I165: 93.8 | J165: 0.54 | K165: 0 | L165: 4.3 | M165: 692008.64 | N165: 116337.87
A166: STR-1042 | B166: 45658 | C166: North | D166: Mall | E166: 72150.53 | F166: 9323 | G166: 0.157 | H166: 22 | I166: 82.9 | J166: 11.37 | K166: 1 | L166: 4.3 | M166: 825797.91 | N166: 130945.24
A167: STR-1042 | B167: 45689 | C167: North | D167: Mall | E167: 35303.3 | F167: 8789 | G167: 0.123 | H167: 22 | I167: 86.1 | J167: 9.43 | K167: 0 | L167: 4.2 | M167: 706285.52 | N167: 138014.72
A168: STR-1042 | B168: 45717 | C168: North | D168: Mall | E168: 30301.86 | F168: 6939 | G168: 0.09 | H168: 16 | I168: 90.3 | J168: 3.49 | K168: 0 | L168: 4 | M168: 665534.7 | N168: 113167.73
A169: STR-1042 | B169: 45748 | C169: North | D169: Mall | E169: 78432.14 | F169: 9440 | G169: 0.126 | H169: 23 | I169: 89.2 | J169: 7.86 | K169: 0 | L169: 4.1 | M169: 820729.29 | N169: 159325.47
A170: STR-1043 | B170: 45658 | C170: East | D170: Residential | E170: 62059.18 | F170: 9374 | G170: 0.136 | H170: 25 | I170: 87.1 | J170: 12.55 | K170: 0 | L170: 4.9 | M170: 739831.73 | N170: 119490.21
A171: STR-1043 | B171: 45689 | C171: East | D171: Residential | E171: 32834.48 | F171: 7576 | G171: 0.099 | H171: 15 | I171: 84.1 | J171: 3.48 | K171: 0 | L171: 5 | M171: 593637.14 | N171: 106648.14
A172: STR-1043 | B172: 45717 | C172: East | D172: Residential | E172: 50825.08 | F172: 8949 | G172: 0.157 | H172: 21 | I172: 84.7 | J172: 7.73 | K172: 0 | L172: 4.9 | M172: 769702.76 | N172: 158697
A173: STR-1043 | B173: 45748 | C173: East | D173: Residential | E173: 36606.51 | F173: 7671 | G173: 0.118 | H173: 18 | I173: 89.8 | J173: 0.25 | K173: 0 | L173: 4.4 | M173: 679731.57 | N173: 121546.42
A174: STR-1044 | B174: 45658 | C174: East | D174: Residential | E174: 65237.79 | F174: 8741 | G174: 0.157 | H174: 20 | I174: 94.4 | J174: 6.43 | K174: 0 | L174: 3.3 | M174: 780344.18 | N174: 118239.09
A175: STR-1044 | B175: 45689 | C175: East | D175: Residential | E175: 43645.98 | F175: 9480 | G175: 0.109 | H175: 22 | I175: 89 | J175: 2.11 | K175: 0 | L175: 3.1 | M175: 721364.11 | N175: 147272.81
A176: STR-1044 | B176: 45717 | C176: East | D176: Residential | E176: 68040.15 | F176: 9826 | G176: 0.125 | H176: 20 | I176: 83.9 | J176: 9.12 | K176: 0 | L176: 3.6 | M176: 758138.29 | N176: 132975.26
... A196: STR-1049 | B196: 45717 | C196: West | D196: Residential | E196: 40220.18 | F196: 3783 | G196: 0.089 | H196: 14 | I196: 86.6 | J196: 3.63 | K196: 0 | L196: 3.7 | M196: 559422.02 | N196: 73528.74
...

Sheet Cleaned_Prepared_Data
A1: store_id | B1: month | C1: region | D1: store_type | E1: marketing_spend | F1: footfall | G1: avg_discount_pct | H1: staff_count | I1: inventory_availability_pct | J1: competitor_distance_km | K1: holiday_flag | L1: customer_rating | M1: monthly_sales | N1: monthly_profit
A2: STR-1001 | B2: 45658 | C2: East | D2: Residential | E2: 70389.11 | F2: 8302 | G2: 0.042 | H2: 17 | I2: 75 | J2: 5.28 | K2: 1 | L2: 3.1 | M2: 658832.62 | N2: 84349.93
A3: STR-1001 | B3: 45689 | C3: East | D3: Residential | E3: 43827.89 | F3: 8487 | G3: 0.168 | H3: 23 | I3: 84.4 | J3: 4.31 | K3: 0 | L3: 2.8 | M3: 634436 | N3: 106130.54
A4: STR-1001 | B4: 45717 | C4: East | D4: Residential | E4: 59921.75 | F4: 9113 | G4: 0.133 | H4: 20 | I4: 88 | J4: 12 | K4: 0 | L4: 3.2 | M4: 678722.06 | N4: 101883.86
A5: STR-1001 | B5: 45748 | C5: East | D5: Residential | E5: 56856.63 | F5: 9431 | G5: 0.142 | H5: 23 | I5: 86.9 | J5: 4.97 | K5: 0 | L5: 3.4 | M5: 658920.3 | N5: 97910.37
A6: STR-1002 | B6: 45658 | C6: East | D6: High Street | E6: 48412.64 | F6: 9545 | G6: 0.231 | H6: 21 | I6: 97.6 | J6: 6.94 | K6: 1 | L6: 4.2 | M6: 741341.44 | N6: 119208.17
A7: STR-1002 | B7: 45689 | C7: East | D7: High Street | E7: 64811.21 | F7: 9792 | G7: 0.112 | H7: 20 | I7: 84.2 | J7: 2.88 | K7: 0 | L7: 4.2 | M7: 761835.34 | N7: 149602.23
A8: STR-1002 | B8: 45717 | C8: East | D8: High Street | E8: 46213.45 | F8: 10616 | G8: 0.122 | H8: 22 | I8: 85.2 | J8: 0.2 | K8: 1 | L8: 4.1 | M8: 806615.54 | N8: 131364.62
A9: STR-1002 | B9: 45748 | C9: East | D9: High Street | E9: 68148.52 | F9: 8567 | G9: 0.127 | H9: 23 | I9: 95.6 | J9: 0.8 | K9: 0 | L9: 3.9 | M9: 850164.26 | N9: 149262.75
A10: STR-1003 | B10: 45658 | C10: North | D10: Airport | E10: 71838.86 | F10: 10979 | G10: 0.215 | H10: 26 | I10: 88.6 | J10: 7.7 | K10: 1 | L10: 3.8 | M10: 930581.7 | N10: 136207.98
A11: STR-1003 | B11: 45689 | C11: North | D11: Airport | E11: 68133.44 | F11: 9459 | G11: 0.22 | H11: 21 | I11: 85 | J11: 1.91 | K11: 0 | L11: 4.2 | M11: 779010.94 | N11: 106328.09
A12: STR-1003 | B12: 45717 | C12: North | D12: Airport | E12: 34285.21 | F12: 9172 | G12: 0.213 | H12: 22 | I12: 88.3 | J12: 10.46 | K12: 1 | L12: 3.8 | M12: 723060.76 | N12: 123131.24
A13: STR-1003 | B13: 45748 | C13: North | D13: Airport | E13: 67979.88 | F13: 11230 | G13: 0.002 | H13: 28 | I13: 85.3 | J13: 7.16 | K13: 0 | L13: 3.8 | M13: 910791.94 | N13: 158891.28
... A321: STR-1080 | B321: 45748 | C321: East | D321: Residential | E321: 40553.11 | F321: 5317 | G321: 0.165 | H321: 17 | I321: 84.3 | J321: 11.82 | K321: 0 | L321: 4.1 | M321: 559660.84 | N321: 71443.61

Sheet Dummy_Variables
A1: store_id | B1: month | C1: marketing_spend | D1: footfall | E1: avg_discount_pct | F1: staff_count | G1: inventory_availability_pct | H1: competitor_distance_km | I1: holiday_flag | J1: customer_rating | K1: monthly_sales | L1: monthly_profit | M1: region_North | N1: region_South | O1: region_West | P1: store_type_High Street | Q1: store_type_Mall | R1: store_type_Residential
A2: STR-1001 | B2: 45658 | C2: 70389.11 | D2: 8302 | E2: 0.042 | F2: 17 | G2: 75 | H2: 5.28 | I2: 1 | J2: 3.1 | K2: 658832.62 | L2: 84349.93 | M2: 0 | N2: 0 | O2: 0 | P2: 0 | Q2: 0 | R2: 1
A3: STR-1001 | B3: 45689 | C3: 43827.89 | D3: 8487 | E3: 0.168 | F3: 23 | G3: 84.4 | H3: 4.31 | I3: 0 | J3: 2.8 | K3: 634436 | L3: 106130.54 | M3: 0 | N3: 0 | O3: 0 | P3: 0 | Q3: 0 | R3: 1
A4: STR-1001 | B4: 45717 | C4: 59921.75 | D4: 9113 | E4: 0.133 | F4: 20 | G4: 88 | H4: 12 | I4: 0 | J4: 3.2 | K4: 678722.06 | L4: 101883.86 | M4: 0 | N4: 0 | O4: 0 | P4: 0 | Q4: 0 | R4: 1
A5: STR-1001 | B5: 45748 | C5: 56856.63 | D5: 9431 | E5: 0.142 | F5: 23 | G5: 86.9 | H5: 4.97 | I5: 0 | J5: 3.4 | K5: 658920.3 | L5: 97910.37 | M5: 0 | N5: 0 | O5: 0 | P5: 0 | Q5: 0 | R5: 1
A6: STR-1002 | B6: 45658 | C6: 48412.64 | D6: 9545 | E6: 0.231 | F6: 21 | G6: 97.6 | H6: 6.94 | I6: 1 | J6: 4.2 | K6: 741341.44 | L6: 119208.17 | M6: 0 | N6: 0 | O6: 0 | P6: 1 | Q6: 0 | R6: 0
A7: STR-1002 | B7: 45689 | C7: 64811.21 | D7: 9792 | E7: 0.112 | F7: 20 | G7: 84.2 | H7: 2.88 | I7: 0 | J7: 4.2 | K7: 761835.34 | L7: 149602.23 | M7: 0 | N7: 0 | O7: 0 | P7: 1 | Q7: 0 | R7: 0
A8: STR-1002 | B8: 45717 | C8: 46213.45 | D8: 10616 | E8: 0.122 | F8: 22 | G8: 85.2 | H8: 0.2 | I8: 1 | J8: 4.1 | K8: 806615.54 | L8: 131364.62 | M8: 0 | N8: 0 | O8: 0 | P8: 1 | Q8: 0 | R8: 0
A9: STR-1002 | B9: 45748 | C9: 68148.52 | D9: 8567 | E9: 0.127 | F9: 23 | G9: 95.6 | H9: 0.8 | I9: 0 | J9: 3.9 | K9: 850164.26 | L9: 149262.75 | M9: 0 | N9: 0 | O9: 0 | P9: 1 | Q9: 0 | R9: 0
A10: STR-1003 | B10: 45658 | C10: 71838.86 | D10: 10979 | E10: 0.215 | F10: 26 | G10: 88.6 | H10: 7.7 | I10: 1 | J10: 3.8 | K10: 930581.7 | L10: 136207.98 | M10: 1 | N10: 0 | O10: 0 | P10: 0 | Q10: 0 | R10: 0
A11: STR-1003 | B11: 45689 | C11: 68133.44 | D11: 9459 | E11: 0.22 | F11: 21 | G11: 85 | H11: 1.91 | I11: 0 | J11: 4.2 | K11: 779010.94 | L11: 106328.09 | M11: 1 | N11: 0 | O11: 0 | P11: 0 | Q11: 0 | R11: 0
A12: STR-1003 | B12: 45717 | C12: 34285.21 | D12: 9172 | E12: 0.213 | F12: 22 | G12: 88.3 | H12: 10.46 | I12: 1 | J12: 3.8 | K12: 723060.76 | L12: 123131.24 | M12: 1 | N12: 0 | O12: 0 | P12: 0 | Q12: 0 | R12: 0
A13: STR-1003 | B13: 45748 | C13: 67979.88 | D13: 11230 | E13: 0.002 | F13: 28 | G13: 85.3 | H13: 7.16 | I13: 0 | J13: 3.8 | K13: 910791.94 | L13: 158891.28 | M13: 1 | N13: 0 | O13: 0 | P13: 0 | Q13: 0 | R13: 0
... A321: STR-1080 | B321: 45748 | C321: 40553.11 | D321: 5317 | E321: 0.165 | F321: 17 | G321: 84.3 | H321: 11.82 | I321: 0 | J321: 4.1 | K321: 559660.84 | L321: 71443.61 | M321: 0 | N321: 0 | O321: 0 | P321: 0 | Q321: 0 | R321: 1

Sheet Simple_Regression_Output
A1: SINGLE REGRESSION ANALYSIS
A2: Model 1: monthly_sales ~ marketing_spend | D2: Coefficient | E2: =SLOPE(B9:B328,A9:A328) -> 2.1295753
D3: Intercept | E3: =INTERCEPT(B9:B328,A9:A328) -> 560777.35
A4: Independent Variable | B4: marketing_spend | D4: R_Squared | E4: =RSQ(B9:B328,A9:A328) -> 0.16724469
A5: Dependent Variable | B5: monthly_sales | D5: Regression Equation | E5: ="monthly_sales = "&ROUND(E3,4)&" + ("&ROUND(E2,4)&" × marketing_spend)" -> monthly_sales = 560777.3454 + (2.1296 × marketing_spend)
D6: P-Value | E6: =_xlfn.F.DIST.RT(E15,1,F15) -> 0
D7: Business Interpretation | E7: For every additional $1.00 spent on marketing, monthly sales are expected to increase by $2.13, proving a positive return on promotional investments. If marketing spend is entirely eliminated, the stores maintain a structural baseline sales level of $560,774.22. Yes. The P-value (2.48E-14) is far below the standard 0.05 threshold, meaning marketing spend is a highly reliable and statistically significant predictor of monthly sales.
A8: marketing_spend | B8: monthly_sales | D8: Variable Appears Useful? | E8: =IF(E6<0.05,"Yes","No") -> Yes
A9: =Cleaned_Prepared_Data!E2 -> 70389.11 | B9: =Cleaned_Prepared_Data!M2 -> 658832.62
A10: =Cleaned_Prepared_Data!E3 -> 43827.89 | B10: =Cleaned_Prepared_Data!M3 -> 634436
A11: =Cleaned_Prepared_Data!E4 -> 59921.75 | B11: =Cleaned_Prepared_Data!M4 -> 678722.06 | E11: LINEST function used below is an array function, it calculates an entire table of regression statistics instantly from a single cell.
A12: =Cleaned_Prepared_Data!E5 -> 56856.63 | B12: =Cleaned_Prepared_Data!M5 -> 658920.3 | E12: {=LINEST(B9:B328, A9:A328, TRUE, TRUE)} -> 2.1295753 | F12: 560777.35
A13: =Cleaned_Prepared_Data!E6 -> 48412.64 | B13: =Cleaned_Prepared_Data!M6 -> 741341.44 | E13: 0.26647838 | F13: 15906.906
A14: =Cleaned_Prepared_Data!E7 -> 64811.21 | B14: =Cleaned_Prepared_Data!M7 -> 761835.34 | E14: 0.16724469 | F14: 94846.034
A15: =Cleaned_Prepared_Data!E8 -> 46213.45 | B15: =Cleaned_Prepared_Data!M8 -> 806615.54 | E15: 63.864873 | F15: 318
A16: =Cleaned_Prepared_Data!E9 -> 68148.52 | B16: =Cleaned_Prepared_Data!M9 -> 850164.26 | E16: 5.7451371e+11 | F16: 2.8606549e+12
A17: =Cleaned_Prepared_Data!E10 -> 71838.86 | B17: =Cleaned_Prepared_Data!M10 -> 930581.7
A18: =Cleaned_Prepared_Data!E11 -> 68133.44 | B18: =Cleaned_Prepared_Data!M11 -> 779010.94
A19: =Cleaned_Prepared_Data!E12 -> 34285.21 | B19: =Cleaned_Prepared_Data!M12 -> 723060.76 | E19: SCROLL DOWN FOR MODEL 2 SINGLE REGRESSION OUTPUT
A20: =Cleaned_Prepared_Data!E13 -> 67979.88 | B20: =Cleaned_Prepared_Data!M13 -> 910791.94
A21: =Cleaned_Prepared_Data!E14 -> 71828.26 | B21: =Cleaned_Prepared_Data!M14 -> 922168.6
A22: =Cleaned_Prepared_Data!E15 -> 55716.82 | B22: =Cleaned_Prepared_Data!M15 -> 726606.28
A23: =Cleaned_Prepared_Data!E16 -> 59909.51 | B23: =Cleaned_Prepared_Data!M16 -> 746501.09
A24: =Cleaned_Prepared_Data!E17 -> 75305.71 | B24: =Cleaned_Prepared_Data!M17 -> 834017.02
A25: =Cleaned_Prepared_Data!E18 -> 48804.22 | B25: =Cleaned_Prepared_Data!M18 -> 666152.52
A26: =Cleaned_Prepared_Data!E19 -> 59117.9 | B26: =Cleaned_Prepared_Data!M19 -> 573155.19
A27: =Cleaned_Prepared_Data!E20 -> 78831.12 | B27: =Cleaned_Prepared_Data!M20 -> 666573.2
A28: =Cleaned_Prepared_Data!E21 -> 41441.93 | B28: =Cleaned_Prepared_Data!M21 -> 591619.95
A29: =Cleaned_Prepared_Data!E22 -> 30356.28 | B29: =Cleaned_Prepared_Data!M22 -> 415721.82
A30: =Cleaned_Prepared_Data!E23 -> 33518.88 | B30: =Cleaned_Prepared_Data!M23 -> 491905.13
A31: =Cleaned_Prepared_Data!E24 -> 42267.37 | B31: =Cleaned_Prepared_Data!M24 -> 555929.4
... A328: =Cleaned_Prepared_Data!E321 -> 40553.11 | B328: =Cleaned_Prepared_Data!M321 -> 559660.84
A342: Model 2: monthly_sales ~ footfall
A344: Dependent Variable | B344: monthly_sales | D344: Coefficient | E344: =SLOPE(B348:B667,A348:A667) -> 35.678031
A345: Independent Variable | B345: footfall | D345: Intercept | E345: =INTERCEPT(B348:B667,A348:A667) -> 446410.58
D346: R_Squared | E346: =RSQ(B348:B667,A348:A667) -> 0.73628534
A347: footfall | B347: monthly_sales | D347: Equation | E347: ="monthly_sales = "&ROUND(E344,4)&" + ("&ROUND(E343,4)&" × footfall)" -> monthly_sales = 35.678 + (0 × footfall)
A348: =Cleaned_Prepared_Data!F2 -> 8302 | B348: =Cleaned_Prepared_Data!M2 -> 658832.62 | D348: P-Value | E348: =_xlfn.F.DIST.RT(E357,1,F357) -> 0
A349: =Cleaned_Prepared_Data!F3 -> 8487 | B349: =Cleaned_Prepared_Data!M3 -> 634436 | D349: Business Interpretation | E349: For every one-unit increase in footfall, monthly_sales changes by the coefficient amount.
A350: =Cleaned_Prepared_Data!F4 -> 9113 | B350: =Cleaned_Prepared_Data!M4 -> 678722.06 | D350: Variable Appears Useful? | E350: =IF(E347<0.05,"Yes","No") -> No
A351: =Cleaned_Prepared_Data!F5 -> 9431 | B351: =Cleaned_Prepared_Data!M5 -> 658920.3
A352: =Cleaned_Prepared_Data!F6 -> 9545 | B352: =Cleaned_Prepared_Data!M6 -> 741341.44
A353: =Cleaned_Prepared_Data!F7 -> 9792 | B353: =Cleaned_Prepared_Data!M7 -> 761835.34 | E353: LINEST function used below is an array function, it calculates an entire table of regression statistics instantly from a single cell.
A354: =Cleaned_Prepared_Data!F8 -> 10616 | B354: =Cleaned_Prepared_Data!M8 -> 806615.54 | E354: {=LINEST(B348:B667,A348:A667,TRUE,TRUE)} -> 35.678031 | F354: 446410.58
A355: =Cleaned_Prepared_Data!F9 -> 8567 | B355: =Cleaned_Prepared_Data!M9 -> 850164.26 | E355: 1.1973783 | F355: 8407.7383
A356: =Cleaned_Prepared_Data!F10 -> 10979 | B356: =Cleaned_Prepared_Data!M10 -> 930581.7 | E356: 0.73628534 | F356: 53373.736
A357: =Cleaned_Prepared_Data!F11 -> 9459 | B357: =Cleaned_Prepared_Data!M11 -> 779010.94 | E357: 887.84878 | F357: 318
A358: =Cleaned_Prepared_Data!F12 -> 9172 | B358: =Cleaned_Prepared_Data!M12 -> 723060.76 | E358: 2.5292643e+12 | F358: 9.0590432e+11
A359: =Cleaned_Prepared_Data!F13 -> 11230 | B359: =Cleaned_Prepared_Data!M13 -> 910791.94
A360: =Cleaned_Prepared_Data!F14 -> 12775 | B360: =Cleaned_Prepared_Data!M14 -> 922168.6
A361: =Cleaned_Prepared_Data!F15 -> 10054 | B361: =Cleaned_Prepared_Data!M15 -> 726606.28
A362: =Cleaned_Prepared_Data!F16 -> 8895 | B362: =Cleaned_Prepared_Data!M16 -> 746501.09
A363: =Cleaned_Prepared_Data!F17 -> 10940 | B363: =Cleaned_Prepared_Data!M17 -> 834017.02
A364: =Cleaned_Prepared_Data!F18 -> 7057 | B364: =Cleaned_Prepared_Data!M18 -> 666152.52
A365: =Cleaned_Prepared_Data!F19 -> 4263 | B365: =Cleaned_Prepared_Data!M19 -> 573155.19
A366: =Cleaned_Prepared_Data!F20 -> 5538 | B366: =Cleaned_Prepared_Data!M20 -> 666573.2
A367: =Cleaned_Prepared_Data!F21 -> 4865 | B367: =Cleaned_Prepared_Data!M21 -> 591619.95
A368: =Cleaned_Prepared_Data!F22 -> 2822 | B368: =Cleaned_Prepared_Data!M22 -> 415721.82
A369: =Cleaned_Prepared_Data!F23 -> 2121 | B369: =Cleaned_Prepared_Data!M23 -> 491905.13
A370: =Cleaned_Prepared_Data!F24 -> 3364 | B370: =Cleaned_Prepared_Data!M24 -> 555929.4
... A667: =Cleaned_Prepared_Data!F321 -> 5317 | B667: =Cleaned_Prepared_Data!M321 -> 559660.84

Sheet Multiple_Regression_Output
A1: Task 5 - Multiple Regression Model
A3: Dependent Variable: monthly_sales
A4: Independent Variables: marketing_spend, footfall, staff_count, holiday_flag
A7: monthly_sales | B7: marketing_spend | C7: footfall | D7: staff_count | E7: holiday_flag
A8: 658832.62 | B8: 70389.11 | C8: 8302 | D8: 17 | E8: 1 | G8: LINEST function used below is an array function, it calculates an entire table of regression statistics instantly from a single cell.
A9: 634436 | B9: 43827.89 | C9: 8487 | D9: 23 | E9: 0 | G9: {=LINEST(A8:A327,{B8:B327,C8:C327,D8:D327,E8:E327},TRUE,TRUE)} -> 10408.002 | H9: 2154.873 | I9: 29.375721 | J9: 1.125386 | K9: 387123.6
A10: 678722.06 | B10: 59921.75 | C10: 9113 | D10: 20 | E10: 0 | G10: 7309.1265 | H10: 1389.0395 | I10: 2.7595254 | J10: 0.14032772 | K10: 11502.06
A11: 658920.3 | B11: 56856.63 | C11: 9431 | D11: 23 | E11: 0 | G11: 0.78476691 | H11: 48447.712 | I11: #N/A | J11: #N/A | K11: #N/A
A12: 741341.44 | B12: 48412.64 | C12: 9545 | D12: 21 | E12: 1 | G12: 287.1324 | H12: 315 | I12: #N/A | J12: #N/A | K12: #N/A
A13: 761835.34 | B13: 64811.21 | C13: 9792 | D13: 20 | E13: 0 | G13: 2.6958067e+12 | H13: 7.3936196e+11 | I13: #N/A | J13: #N/A | K13: #N/A
A14: 806615.54 | B14: 46213.45 | C14: 10616 | D14: 22 | E14: 1
A15: 850164.26 | B15: 68148.52 | C15: 8567 | D15: 23 | E15: 0
A16: 930581.7 | B16: 71838.86 | C16: 10979 | D16: 26 | E16: 1 | G16: Variable | H16: Coefficient | I16: Std Error | J16: t-Statistic | K16: P-Value | L16: Significant?
A17: 779010.94 | B17: 68133.44 | C17: 9459 | D17: 21 | E17: 0 | G17: holiday_flag | H17: =G9 -> 10408.002 | I17: =G10 -> 7309.1265 | J17: =H17/I17 -> 1.4239735 | K17: =_xlfn.T.DIST.2T(ABS(J17),$H$12) -> 0.15544396 | L17: =IF(K17<0.05,"Yes","No") -> No
A18: 723060.76 | B18: 34285.21 | C18: 9172 | D18: 22 | E18: 1 | G18: staff_count | H18: =H9 -> 2154.873 | I18: =H10 -> 1389.0394 | J18: =H18/I18 -> 1.5513404 | K18: =_xlfn.T.DIST.2T(ABS(J18),$H$12) -> 0.12182422 | L18: =IF(K18<0.05,"Yes","No") -> No
A19: 910791.94 | B19: 67979.88 | C19: 11230 | D19: 28 | E19: 0 | G19: footfall | H19: =I9 -> 29.375721 | I19: =I10 -> 2.7595254 | J19: =H19/I19 -> 10.645208 | K19: =_xlfn.T.DIST.2T(ABS(J19),$H$12) -> 0 | L19: =IF(K19<0.05,"Yes","No") -> Yes
A20: 922168.6 | B20: 71828.26 | C20: 12775 | D20: 30 | E20: 1 | G20: marketing_spend | H20: =J9 -> 1.125386 | I20: =J10 -> 0.14032772 | J20: =H20/I20 -> 8.0196985 | K20: =_xlfn.T.DIST.2T(ABS(J20),$H$12) -> 0 | L20: =IF(K20<0.05,"Yes","No") -> Yes
A21: 726606.28 | B21: 55716.82 | C21: 10054 | D21: 24 | E21: 0
A22: 746501.09 | B22: 59909.51 | C22: 8895 | D22: 23 | E22: 0
A23: 834017.02 | B23: 75305.71 | C23: 10940 | D23: 26 | E23: 0
A24: 666152.52 | B24: 48804.22 | C24: 7057 | D24: 15 | E24: 0
A25: 573155.19 | B25: 59117.9 | C25: 4263 | D25: 9 | E25: 0
A26: 666573.2 | B26: 78831.12 | C26: 5538 | D26: 15 | E26: 0
A27: 591619.95 | B27: 41441.93 | C27: 4865 | D27: 16 | E27: 0
A28: 415721.82 | B28: 30356.28 | C28: 2822 | D28: 9 | E28: 0
A29: 491905.13 | B29: 33518.88 | C29: 2121 | D29: 8 | E29: 0
A30: 555929.4 | B30: 42267.37 | C30: 3364 | D30: 13 | E30: 1
A31: 565810.99 | B31: 62060.43 | C31: 2613 | D31: 12 | E31: 0
A32: 811771.14 | B32: 57696.69 | C32: 10218 | D32: 25 | E32: 0
... A327: 559660.84 | B327: 40553.11 | C327: 5317 | D327: 17 | E327: 0

Sheet Predictions_Residuals
A1: monthly_sales | B1: marketing_spend | C1: footfall | D1: staff_count | E1: holiday_flag | F1: Predicted_Sales | G1: Residual | H1: Residual_Squared | I1: Absolute_Residual | K1: Metric | L1: Value
A2: 658832.62 | B2: 70389.11 | C2: 8302 | D2: 17 | E2: 1 | F2: =387123.6029+(1.125386035*B2)+(29.37572083*C2)+(2154.873038*D2)+(10408.00247*E2) -> 757256.6 | G2: =A2-F2 -> -98423.983 | H2: =G2^2 -> 9687280382 | I2: =ABS(G2) -> 98423.983 | K2: Mean Residual | L2: =AVERAGE(G2:G321) -> -2.8844935e-05
A3: 634436 | B3: 43827.89 | C3: 8487 | D3: 23 | E3: 0 | F3: =387123.6029+(1.125386035*B3)+(29.37572083*C3)+(2154.873038*D3)+(10408.00247*E3) -> 735320.72 | G3: =A3-F3 -> -100884.72 | H3: =G3^2 -> 10177726892 | I3: =ABS(G3) -> 100884.72 | K3: Maximum Residual | L3: =MAX(G2:G321) -> 121902.4
A4: 678722.06 | B4: 59921.75 | C4: 9113 | D4: 20 | E4: 0 | F4: =387123.6029+(1.125386035*B4)+(29.37572083*C4)+(2154.873038*D4)+(10408.00247*E4) -> 765357.11 | G4: =A4-F4 -> -86635.048 | H4: =G4^2 -> 7505631581 | I4: =ABS(G4) -> 86635.048 | K4: Minimum Residual | L4: =MIN(G2:G321) -> -135692.98
A5: 658920.3 | B5: 56856.63 | C5: 9431 | D5: 23 | E5: 0 | F5: =387123.6029+(1.125386035*B5)+(29.37572083*C5)+(2154.873038*D5)+(10408.00247*E5) -> 777713.76 | G5: =A5-F5 -> -118793.46 | H5: =G5^2 -> 14111886928 | I5: =ABS(G5) -> 118793.46 | K5: Mean Absolute Residual | L5: =AVERAGE(I2:I321) -> 37607.952
A6: 741341.44 | B6: 48412.64 | C6: 9545 | D6: 21 | E6: 1 | F6: =387123.6029+(1.125386035*B6)+(29.37572083*C6)+(2154.873038*D6)+(10408.00247*E6) -> 777658.1 | G6: =A6-F6 -> -36316.663 | H6: =G6^2 -> 1318900045 | I6: =ABS(G6) -> 36316.663 | K6: Residual Standard Deviation | L6: =STDEV(G2:G321) -> 48143.007
A7: 761835.34 | B7: 64811.21 | C7: 9792 | D7: 20 | E7: 0 | F7: =387123.6029+(1.125386035*B7)+(29.37572083*C7)+(2154.873038*D7)+(10408.00247*E7) -> 790805.75 | G7: =A7-F7 -> -28970.413 | H7: =G7^2 -> 8.3928481e+08 | I7: =ABS(G7) -> 28970.413
A8: 806615.54 | B8: 46213.45 | C8: 10616 | D8: 22 | E8: 1 | F8: =387123.6029+(1.125386035*B8)+(29.37572083*C8)+(2154.873038*D8)+(10408.00247*E8) -> 808799.44 | G8: =A8-F8 -> -2183.8958 | H8: =G8^2 -> 4769400.8 | I8: =ABS(G8) -> 2183.8958
A9: 850164.26 | B9: 68148.52 | C9: 8567 | D9: 23 | E9: 0 | F9: =387123.6029+(1.125386035*B9)+(29.37572083*C9)+(2154.873038*D9)+(10408.00247*E9) -> 765040.88 | G9: =A9-F9 -> 85123.384 | H9: =G9^2 -> 7245990531 | I9: =ABS(G9) -> 85123.384
A10: 930581.7 | B10: 71838.86 | C10: 10979 | D10: 26 | E10: 1 | F10: =387123.6029+(1.125386035*B10)+(29.37572083*C10)+(2154.873038*D10)+(10408.00247*E10) -> 856920.79 | G10: =A10-F10 -> 73660.907 | H10: =G10^2 -> 5425929196 | I10: =ABS(G10) -> 73660.907
A11: 779010.94 | B11: 68133.44 | C11: 9459 | D11: 21 | E11: 0 | F11: =387123.6029+(1.125386035*B11)+(29.37572083*C11)+(2154.873038*D11)+(10408.00247*E11) -> 786917.3 | G11: =A11-F11 -> -7906.3619 | H11: =G11^2 -> 62510559 | I11: =ABS(G11) -> 7906.3619
A12: 723060.76 | B12: 34285.21 | C12: 9172 | D12: 22 | E12: 1 | F12: =387123.6029+(1.125386035*B12)+(29.37572083*C12)+(2154.873038*D12)+(10408.00247*E12) -> 752957.02 | G12: =A12-F12 -> -29896.26 | H12: =G12^2 -> 8.9378637e+08 | I12: =ABS(G12) -> 29896.26
A13: 910791.94 | B13: 67979.88 | C13: 11230 | D13: 28 | E13: 0 | F13: =387123.6029+(1.125386035*B13)+(29.37572083*C13)+(2154.873038*D13)+(10408.00247*E13) -> 853853 | G13: =A13-F13 -> 56938.94 | H13: =G13^2 -> 3242042832 | I13: =ABS(G13) -> 56938.94 | K13: RESIDUAL ANALYSIS
A14: 922168.6 | B14: 71828.26 | C14: 12775 | D14: 30 | E14: 1 | F14: =387123.6029+(1.125386035*B14)+(29.37572083*C14)+(2154.873038*D14)+(10408.00247*E14) -> 918287.15 | G14: =A14-F14 -> 3881.4492 | H14: =G14^2 -> 15065648 | I14: =ABS(G14) -> 3881.4492
A15: 726606.28 | B15: 55716.82 | C15: 10054 | D15: 24 | E15: 0 | F15: =387123.6029+(1.125386035*B15)+(29.37572083*C15)+(2154.873038*D15)+(10408.00247*E15) -> 796886.98 | G15: =A15-F15 -> -70280.704 | H15: =G15^2 -> 4939377380 | I15: =ABS(G15) -> 70280.704
A16: 746501.09 | B16: 59909.51 | C16: 8895 | D16: 23 | E16: 0 | F16: =387123.6029+(1.125386035*B16)+(29.37572083*C16)+(2154.873038*D16)+(10408.00247*E16) -> 765404.05 | G16: =A16-F16 -> -18902.955 | H16: =G16^2 -> 3.5732173e+08 | I16: =ABS(G16) -> 18902.955
A17: 834017.02 | B17: 75305.71 | C17: 10940 | D17: 26 | E17: 0 | F17: =387123.6029+(1.125386035*B17)+(29.37572083*C17)+(2154.873038*D17)+(10408.00247*E17) -> 849268.68 | G17: =A17-F17 -> -15251.662 | H17: =G17^2 -> 2.326132e+08 | I17: =ABS(G17) -> 15251.662
A18: 666152.52 | B18: 48804.22 | C18: 7057 | D18: 15 | E18: 0 | F18: =387123.6029+(1.125386035*B18)+(29.37572083*C18)+(2154.873038*D18)+(10408.00247*E18) -> 681674.75 | G18: =A18-F18 -> -15522.228 | H18: =G18^2 -> 2.4093956e+08 | I18: =ABS(G18) -> 15522.228
A19: 573155.19 | B19: 59117.9 | C19: 4263 | D19: 9 | E19: 0 | F19: =387123.6029+(1.125386035*B19)+(29.37572083*C19)+(2154.873038*D19)+(10408.00247*E19) -> 598276.62 | G19: =A19-F19 -> -25121.427 | H19: =G19^2 -> 6.3108611e+08 | I19: =ABS(G19) -> 25121.427
A20: 666573.2 | B20: 78831.12 | C20: 5538 | D20: 15 | E20: 0 | F20: =387123.6029+(1.125386035*B20)+(29.37572083*C20)+(2154.873038*D20)+(10408.00247*E20) -> 670844.88 | G20: =A20-F20 -> -4271.682 | H20: =G20^2 -> 18247267 | I20: =ABS(G20) -> 4271.682
A21: 591619.95 | B21: 41441.93 | C21: 4865 | D21: 16 | E21: 0 | F21: =387123.6029+(1.125386035*B21)+(29.37572083*C21)+(2154.873038*D21)+(10408.00247*E21) -> 611152.62 | G21: =A21-F21 -> -19532.673 | H21: =G21^2 -> 3.815253e+08 | I21: =ABS(G21) -> 19532.673
A22: 415721.82 | B22: 30356.28 | C22: 2822 | D22: 9 | E22: 0 | F22: =387123.6029+(1.125386035*B22)+(29.37572083*C22)+(2154.873038*D22)+(10408.00247*E22) -> 523578.28 | G22: =A22-F22 -> -107856.46 | H22: =G22^2 -> 11633015535 | I22: =ABS(G22) -> 107856.46
A23: 491905.13 | B23: 33518.88 | C23: 2121 | D23: 8 | E23: 0 | F23: =387123.6029+(1.125386035*B23)+(29.37572083*C23)+(2154.873038*D23)+(10408.00247*E23) -> 504390.17 | G23: =A23-F23 -> -12485.041 | H23: =G23^2 -> 1.5587624e+08 | I23: =ABS(G23) -> 12485.041
A24: 555929.4 | B24: 42267.37 | C24: 3364 | D24: 13 | E24: 1 | F24: =387123.6029+(1.125386035*B24)+(29.37572083*C24)+(2154.873038*D24)+(10408.00247*E24) -> 571931.99 | G24: =A24-F24 -> -16002.588 | H24: =G24^2 -> 2.5608281e+08 | I24: =ABS(G24) -> 16002.588
A25: 565810.99 | B25: 62060.43 | C25: 2613 | D25: 12 | E25: 0 | F25: =387123.6029+(1.125386035*B25)+(29.37572083*C25)+(2154.873038*D25)+(10408.00247*E25) -> 559582.78 | G25: =A25-F25 -> 6228.2109 | H25: =G25^2 -> 38790611 | I25: =ABS(G25) -> 6228.2109
... A321: 559660.84 | B321: 40553.11 | C321: 5317 | D321: 17 | E321: 0 | F321: =387123.6029+(1.125386035*B321)+(29.37572083*C321)+(2154.873038*D321)+(10408.00247*E321) -> 625585.06 | G321: =A321-F321 -> -65924.216 | H321: =G321^2 -> 4346002238 | I321: =ABS(G321) -> 65924.216

Sheet Model_Comparison
A1: MODEL COMPARISON
A3: Model | B3: Dependent Variable | C3: Independent Variables | D3: R-Squared | E3: Significant Variables | F3: Business Usefulness
A4: Simple Regression 1 | B4: monthly_sales | C4: marketing_spend | D4: 0.1672 | E4: marketing_spend | F4: Measures the impact of marketing investment on sales
A5: Simple Regression 2 | B5: monthly_sales | C5: footfall | D5: 0.7363 | E5: footfall | F5: Measures the impact of customer traffic on sales
A6: Multiple Regression | B6: monthly_sales | C6: marketing_spend, footfall, staff_count, holiday_flag | D6: 0.7848 | E6: marketing_spend, footfall | F6: Evaluates multiple sales drivers simultaneously
A10: Rank | B10: Model | C10: R-Squared | D10: Reason
A11: 1 | B11: Multiple Regression | C11: 0.7848 | D11: Highest explanatory power and includes multiple predictors
A12: 2 | B12: Simple Regression 2 (Footfall) | C12: 0.7363 | D12: Strong predictor with high explanatory power
A13: 3 | B13: Simple Regression 1 (Marketing Spend) | C13: 0.1672 | D13: Lowest explanatory power among the models
